normliv/__init__.py
normliv/norm.py
normliv-0.1.0.dist-info/LICENCE
normliv-0.1.0.dist-info/METADATA
normliv-0.1.0.dist-info/WHEEL
normliv-0.1.0.dist-info/top_level.txt
normliv-0.1.0.dist-info/RECORD
