Metadata-Version: 2.1
Name: normliv
Version: 0.1.0
Summary: A package to normalize Livonian orthography
Author: Jules Bouton
Project-URL: Homepage, https://gitlab.com/finug/normalize-livonian
Project-URL: Issues, https://gitlab.com/finug/normalize-livonian/issues
Classifier: Programming Language :: Python :: 3
Classifier: License :: OSI Approved :: GNU General Public License v3 (GPLv3)
Classifier: Operating System :: OS Independent
Requires-Python: >=3.8
License-File: LICENCE
